streamlit_scroll_navigation/__init__.py
streamlit_scroll_navigation/frontend/.prettierrc
streamlit_scroll_navigation/frontend/package-lock.json
streamlit_scroll_navigation/frontend/package.json
streamlit_scroll_navigation/frontend/tsconfig.json
streamlit_scroll_navigation/frontend/build/CrossOriginInterface.js
streamlit_scroll_navigation/frontend/build/CrossOriginInterface.min.js
streamlit_scroll_navigation/frontend/build/asset-manifest.json
streamlit_scroll_navigation/frontend/build/bootstrap.min.css
streamlit_scroll_navigation/frontend/build/index.html
streamlit_scroll_navigation/frontend/build/static/css/main.72fa2d8c.css
streamlit_scroll_navigation/frontend/build/static/css/main.72fa2d8c.css.map
streamlit_scroll_navigation/frontend/build/static/js/main.82444e30.js
streamlit_scroll_navigation/frontend/build/static/js/main.82444e30.js.LICENSE.txt
streamlit_scroll_navigation/frontend/build/static/js/main.82444e30.js.map
streamlit_scroll_navigation/frontend/build/static/media/bootstrap-icons.39795c0b4513de014cf8.woff
streamlit_scroll_navigation/frontend/build/static/media/bootstrap-icons.b7bcc075b395c14ce8c2.woff2
streamlit_scroll_navigation/frontend/node_modules/flatted/python/flatted.py
streamlit_scroll_navigation/frontend/node_modules/flatted/python/test.py
streamlit_scroll_navigation/frontend/public/CrossOriginInterface.js
streamlit_scroll_navigation/frontend/public/bootstrap.min.css
streamlit_scroll_navigation/frontend/public/index.html
streamlit_scroll_navigation/frontend/src/ScrollNavigationBar.tsx
streamlit_scroll_navigation/frontend/src/index.css
streamlit_scroll_navigation/frontend/src/index.tsx
streamlit_scroll_navigation/frontend/src/react-app-env.d.ts
streamlit_scroll_navigation-1.2.1.dist-info/LICENSE
streamlit_scroll_navigation-1.2.1.dist-info/METADATA
streamlit_scroll_navigation-1.2.1.dist-info/WHEEL
streamlit_scroll_navigation-1.2.1.dist-info/top_level.txt
streamlit_scroll_navigation-1.2.1.dist-info/RECORD
