Metadata-Version: 2.1
Name: streamlit-scroll-navigation
Version: 1.2.1
Summary: Streamlit component for scroll-based page navigation.
Author: Nibs
License: MIT
Project-URL: homepage, https://github.com/snpm/streamlit-scroll-navigation/
Classifier: Development Status :: 5 - Production/Stable
Classifier: Intended Audience :: Developers
Classifier: License :: OSI Approved :: MIT License
Classifier: Programming Language :: Python
Classifier: Programming Language :: Python :: 3
Classifier: Programming Language :: Python :: 3.7
Classifier: Programming Language :: Python :: 3.8
Classifier: Programming Language :: Python :: 3.9
Classifier: Programming Language :: Python :: 3.10
Classifier: Topic :: Software Development :: Libraries
Classifier: Topic :: Software Development :: Libraries :: Python Modules
Requires-Python: >=3.7
License-File: LICENSE
Requires-Dist: streamlit>=1.0
Provides-Extra: devel
Requires-Dist: wheel; extra == "devel"
Requires-Dist: twine; extra == "devel"
Requires-Dist: setuptools>=42; extra == "devel"
